magic_top_hat/__init__.py
magic_top_hat-0.1.0.dist-info/METADATA
magic_top_hat-0.1.0.dist-info/WHEEL
magic_top_hat-0.1.0.dist-info/RECORD
