Metadata-Version: 2.3
Name: magic_top_hat
Version: 0.1.0
Summary: Add your description here
Author-email: Luca Mattiazzi <l.d.mattiazzi@gmail.com>
Requires-Python: >=3.8
Requires-Dist: openai>=1.35.13
Requires-Dist: python-dotenv>=1.0.1
